{
  "nodes": [
    {
      "id": 0,
      "x": 1504.166666666667,
      "y": 6091.868131868132
    },
    {
      "id": 1,
      "x": 1987.5000000000005,
      "y": 6091.868131868132
    },
    {
      "id": 2,
      "x": 2187.5000000000005,
      "y": 6091.868131868132
    },
    {
      "id": 3,
      "x": 2195.8333333333335,
      "y": 5883.076923076924
    },
    {
      "id": 4,
      "x": 3387.5,
      "y": 5891.428571428572
    },
    {
      "id": 5,
      "x": 3987.5,
      "y": 5883.076923076924
    },
    {
      "id": 6,
      "x": 3979.166666666667,
      "y": 5290.10989010989
    },
    {
      "id": 7,
      "x": 3387.5,
      "y": 5290.10989010989
    },
    {
      "id": 8,
      "x": 2204.166666666667,
      "y": 5298.461538461539
    },
    {
      "id": 9,
      "x": 3379.166666666667,
      "y": 4688.791208791209
    },
    {
      "id": 10,
      "x": 2204.166666666667,
      "y": 4680.43956043956
    },
    {
      "id": 11,
      "x": 2195.8333333333335,
      "y": 3294.065934065934
    },
    {
      "id": 12,
      "x": 3387.5,
      "y": 3277.3626373626375
    },
    {
      "id": 13,
      "x": 3395.833333333334,
      "y": 1490.1098901098903
    },
    {
      "id": 14,
      "x": 3979.166666666667,
      "y": 1490.1098901098903
    },
    {
      "id": 15,
      "x": 3979.166666666667,
      "y": 2083.0769230769233
    },
    {
      "id": 16,
      "x": 5987.500000000001,
      "y": 2083.0769230769233
    }
  ],
  "edges": [
    {
      "id": 0,
      "startNodeId": 0,
      "endNodeId": 1,
      "weight": 483.3333333333335
    },
    {
      "id": 1,
      "startNodeId": 1,
      "endNodeId": 2,
      "weight": 200
    },
    {
      "id": 2,
      "startNodeId": 2,
      "endNodeId": 3,
      "weight": 208.95744378446614
    },
    {
      "id": 3,
      "startNodeId": 3,
      "endNodeId": 4,
      "weight": 1191.6959320542442
    },
    {
      "id": 4,
      "startNodeId": 4,
      "endNodeId": 5,
      "weight": 600.0581222099986
    },
    {
      "id": 5,
      "startNodeId": 5,
      "endNodeId": 6,
      "weight": 593.0255868258732
    },
    {
      "id": 6,
      "startNodeId": 6,
      "endNodeId": 7,
      "weight": 591.666666666667
    },
    {
      "id": 7,
      "startNodeId": 7,
      "endNodeId": 8,
      "weight": 1183.3628048100745
    },
    {
      "id": 8,
      "startNodeId": 8,
      "endNodeId": 3,
      "weight": 584.674774873552
    },
    {
      "id": 9,
      "startNodeId": 4,
      "endNodeId": 7,
      "weight": 601.3186813186812
    },
    {
      "id": 10,
      "startNodeId": 7,
      "endNodeId": 9,
      "weight": 601.3764220081148
    },
    {
      "id": 11,
      "startNodeId": 9,
      "endNodeId": 10,
      "weight": 1175.029680489046
    },
    {
      "id": 12,
      "startNodeId": 10,
      "endNodeId": 11,
      "weight": 1386.3986715042697
    },
    {
      "id": 13,
      "startNodeId": 11,
      "endNodeId": 12,
      "weight": 1191.7837239051398
    },
    {
      "id": 14,
      "startNodeId": 12,
      "endNodeId": 13,
      "weight": 1787.2721748538852
    },
    {
      "id": 15,
      "startNodeId": 13,
      "endNodeId": 14,
      "weight": 583.333333333333
    },
    {
      "id": 16,
      "startNodeId": 14,
      "endNodeId": 15,
      "weight": 592.967032967033
    },
    {
      "id": 17,
      "startNodeId": 15,
      "endNodeId": 16,
      "weight": 2008.333333333334
    }
  ]
}
